COPYING
Changes
GPL-2
README
TODO
ez_setup.py
setup.py
debian/changelog
debian/compat
debian/control
debian/copyright
debian/docs
debian/rules
debian/watch
doc/html-de/Liste_der_Schlüsselwörter.html
doc/html-de/Quiz_schreiben.html
doc/html-de/Quizdrill.html
doc/html-de/index.html
doc/html-en/Hacking.html
doc/html-en/Install.html
doc/html-en/List_of_Quizzes.html
doc/html-en/Quizdrill.html
doc/html-en/Similar_Programs.html
doc/html-en/Usage.html
doc/html-en/Writing_Quizzes.html
doc/html-en/index.html
po/POTFILES.in
po/POTFILES.skip
po/de.po
quizdrill.egg-info/PKG-INFO
quizdrill.egg-info/SOURCES.txt
quizdrill.egg-info/dependency_links.txt
quizdrill.egg-info/entry_points.txt
quizdrill.egg-info/top_level.txt
quizzes/deu-fra.drill
quizzes/deu-svd.drill
quizzes/deu_Gemälde.drill
quizzes/deu_Hauptstädte.drill
quizzes/deu_Muskelatur.drill
quizzes/deu_Opern.drill
quizzes/eng-fra.drill
quizzes/eng-jpn.drill
quizzes/eng-jpn_romaji.drill
quizzes/eng-svd.drill
quizzes/fra_verb.drill
quizzes/builder/deu_Gemälde.drill.builder
quizzes/builder/deu_Gemälde.drill.original
quizzes/builder/deu_Hauptstädte.drill.builder
quizzes/builder/deu_Hauptstädte.drill.original
quizzes/builder/deu_Muskelatur.drill.builder
quizzes/builder/deu_Muskelatur.drill.original
quizzes/builder/deu_Opern.drill.builder
quizzes/builder/deu_Opern.drill.original
src/SaDrill.py
src/__init__.py
src/builder.py
src/quizdrill.py
src/data/quizdrill.glade
src/data/quizdrill.schemas.in
src/data/locale/de/LC_MESSAGES/quizdrill.mo
