Metadata-Version: 1.0
Name: quizdrill
Version: 0.2.0
Summary: A learning-by-testing to excess program.
Home-page: http://quizdrill.berlios.de/
Author: Adam Schmalhofer
Author-email: schmalhof@users.berlios.de
License: GNU General Public License
Platform: any
Classifier: Development Status :: 4 - Beta
Classifier: Environment :: X11 Applications :: Gnome
Classifier: Intended Audience :: Education
Classifier: Intended Audience :: End Users/Desktop
Classifier: License :: OSI Approved :: GNU General Public License (GPL)
Classifier: Natural Language :: English
Classifier: Natural Language :: German
Classifier: Operating System :: OS Independent
Classifier: Programming Language :: Python
Classifier: Topic :: Education :: Testing
